AUTHORS.org
LICENSE
MANIFEST.in
README.org
pyproject.toml
requirements.in
setup.cfg
setup.py
envs/dev/dev.requirements.list
envs/dev/env.yaml
envs/dev/py_version.txt
envs/dev/requirements.in
envs/dev/requirements.txt
envs/dev/self.requirements.txt
envs/test_install/pyversion.txt
envs/test_install/pyversion.txt~
envs/test_install/requirements.in
envs/test_install/requirements.txt
envs/test_install/self.requirements.txt
info/README.org
info/changelog.org
info/dev_guide.org
info/general_info.org
info/glossary.rst
info/installation.org
info/introduction.org
info/news.org
info/quick_start.org
info/reference.org
info/troubleshooting.org
info/users_guide.org
info/examples/.keep
info/examples/ex1.py
info/examples/ex1.py~
info/tutorials/example.org
info/tutorials/index.rst
sphinx/Makefile
sphinx/conf.py
sphinx/index.rst
src/py_rsync/__init__.py
src/py_rsync/_print_version.py
src/py_rsync/_version.py
src/py_rsync/main.py
src/py_rsync/main.py~
src/py_rsync/main.y~
src/py_rsync.egg-info/PKG-INFO
src/py_rsync.egg-info/SOURCES.txt
src/py_rsync.egg-info/dependency_links.txt
src/py_rsync.egg-info/entry_points.txt
src/py_rsync.egg-info/requires.txt
src/py_rsync.egg-info/top_level.txt
src/py_rsync/rsync_template/__init__.py
src/py_rsync/rsync_template/rsync_command.txt.j2
src/py_rsync/rsync_template/rsync_command.txt.j2~
src/py_rsync/rsync_template/rsync_endpoint.txt.j2~