Metadata-Version: 2.1
Name: py-rsync
Version: 0.0.1a0.dev0
Summary: Wrapper around rsync command line for building complex commands
Home-page: https://github.com/salotz/py_rsync
Author: Samuel D. Lotz
Author-email: samuel.lotz@salotz.info
License: MIT
Platform: UNKNOWN
Classifier: Topic :: Utilities
Classifier: License :: OSI Approved :: MIT License
Classifier: Programming Language :: Python :: 3
Provides-Extra: all
